pyams_security/__init__.py
pyams_security/credential.py
pyams_security/include.py
pyams_security/index.py
pyams_security/monitor.py
pyams_security/notification.py
pyams_security/password.py
pyams_security/permission.py
pyams_security/policy.py
pyams_security/principal.py
pyams_security/profile.py
pyams_security/property.py
pyams_security/rest.py
pyams_security/role.py
pyams_security/schema.py
pyams_security/security.py
pyams_security/site.py
pyams_security/utility.py
pyams_security/vocabulary.py
pyams_security/api/__init__.py
pyams_security/doctests/README.rst
pyams_security/doctests/credentials.rst
pyams_security/doctests/manager.rst
pyams_security/doctests/notifications.rst
pyams_security/doctests/passwords.rst
pyams_security/doctests/plugins.rst
pyams_security/doctests/policy.rst
pyams_security/doctests/principals.rst
pyams_security/doctests/profiles.rst
pyams_security/doctests/rest.rst
pyams_security/doctests/roles.rst
pyams_security/doctests/security.rst
pyams_security/doctests/users.rst
pyams_security/generations/__init__.py
pyams_security/generations/evolve1.py
pyams_security/interfaces/__init__.py
pyams_security/interfaces/base.py
pyams_security/interfaces/names.py
pyams_security/interfaces/notification.py
pyams_security/interfaces/plugin.py
pyams_security/interfaces/profile.py
pyams_security/interfaces/rest.py
pyams_security/interfaces/site.py
pyams_security/locales/pyams_security.pot
pyams_security/locales/fr/LC_MESSAGES/pyams_security.mo
pyams_security/locales/fr/LC_MESSAGES/pyams_security.po
pyams_security/plugin/__init__.py
pyams_security/plugin/admin.py
pyams_security/plugin/group.py
pyams_security/plugin/userfolder.py
pyams_security/plugin/templates/password-reset.pt
pyams_security/plugin/templates/register-body.pt
pyams_security/plugin/templates/register-info.pt
pyams_security/plugin/templates/register-message.pt
pyams_security/tests/__init__.py
pyams_security/tests/test_utilsdocs.py
pyams_security/tests/test_utilsdocstrings.py
pyams_security-2.7.0.dist-info/LICENSE
pyams_security-2.7.0.dist-info/METADATA
pyams_security-2.7.0.dist-info/WHEEL
pyams_security-2.7.0.dist-info/entry_points.txt
pyams_security-2.7.0.dist-info/namespace_packages.txt
pyams_security-2.7.0.dist-info/top_level.txt
pyams_security-2.7.0.dist-info/RECORD
