Metadata-Version: 2.1
Name: pyams-security
Version: 2.7.0
Summary: PyAMS security management package
Home-page: https://pyams.readthedocs.io
Author: Thierry Florac
Author-email: tflorac@ulthar.net
License: ZPL
Keywords: Pyramid PyAMS
Classifier: License :: OSI Approved :: Zope Public License
Classifier: Development Status :: 4 - Beta
Classifier: Programming Language :: Python
Classifier: Framework :: Pyramid
Classifier: Topic :: Software Development :: Libraries :: Python Modules
Requires-Python: >=3.7
License-File: LICENSE
Requires-Dist: setuptools
Requires-Dist: BTrees
Requires-Dist: ZODB
Requires-Dist: beaker
Requires-Dist: chameleon
Requires-Dist: hypatia
Requires-Dist: persistent
Requires-Dist: pyams-file
Requires-Dist: pyams-i18n
Requires-Dist: pyams-mail
Requires-Dist: pyams-site
Requires-Dist: pyams-utils >=2.8.0
Requires-Dist: pyramid >=2.0.0
Requires-Dist: pyramid-chameleon
Requires-Dist: pyramid-mailer
Requires-Dist: zodbupdate
Requires-Dist: zope.annotation
Requires-Dist: zope.component
Requires-Dist: zope.componentvocabulary
Requires-Dist: zope.container
Requires-Dist: zope.interface
Requires-Dist: zope.intid
Requires-Dist: zope.lifecycleevent
Requires-Dist: zope.location
Requires-Dist: zope.password
Requires-Dist: zope.principalannotation
Requires-Dist: zope.schema
Requires-Dist: zope.traversing
Provides-Extra: test
Requires-Dist: pyams-catalog ; extra == 'test'
Requires-Dist: pyams-zmi ; extra == 'test'
